{
    "kind": "class",
    "name": "CAnimationGroup",
    "description": "",
    "constructor": {
        "arguments": {
            "ptr_or_class": "SDKClass|string"
        },
        "return": "CAnimationGroup"
    },
    "properties": [
        {
            "name": "Flags",
            "type": "uint32",
            "writable": true
        },
        {
            "name": "DecodeKey",
            "type": "CAnimKeyData",
            "writable": false
        }
    ],
    "functions": [
        {
            "name": "ToPtr",
            "arguments": {},
            "return": "string"
        },
        {
            "name": "IsValid",
            "arguments": {},
            "return": "bool"
        }
    ],
    "games": [
        "cs2"
    ]
}