{
    "kind": "class",
    "name": "CPointTeleportAPI",
    "description": "",
    "constructor": {
        "arguments": {
            "ptr_or_class": "SDKClass|string"
        },
        "return": "CPointTeleportAPI"
    },
    "properties": [],
    "functions": [
        {
            "name": "ToPtr",
            "arguments": {},
            "return": "string"
        },
        {
            "name": "IsValid",
            "arguments": {},
            "return": "bool"
        }
    ],
    "games": [
        "cs2"
    ]
}