{
    "kind": "class",
    "name": "ModelConfigHandle_t",
    "description": "",
    "constructor": {
        "arguments": {
            "ptr_or_class": "SDKClass|string"
        },
        "return": "ModelConfigHandle_t"
    },
    "properties": [
        {
            "name": "Value",
            "type": "uint32",
            "writable": true
        }
    ],
    "functions": [
        {
            "name": "ToPtr",
            "arguments": {},
            "return": "string"
        },
        {
            "name": "IsValid",
            "arguments": {},
            "return": "bool"
        }
    ],
    "games": [
        "cs2"
    ]
}